examples/__init__.py
examples/demo.py
miwork/__init__.py
miwork/__version__.py
miwork/api.py
miwork/api_app_link.py
miwork/api_application.py
miwork/api_approval.py
miwork/api_bot.py
miwork/api_calendar.py
miwork/api_callback.py
miwork/api_chat.py
miwork/api_contact.py
miwork/api_drive_comment.py
miwork/api_drive_doc.py
miwork/api_drive_file.py
miwork/api_drive_folder.py
miwork/api_drive_permission.py
miwork/api_drive_sheet.py
miwork/api_drive_suite.py
miwork/api_duty.py
miwork/api_file.py
miwork/api_id.py
miwork/api_image.py
miwork/api_meeting_room.py
miwork/api_message.py
miwork/api_mina.py
miwork/api_oauth.py
miwork/api_pay.py
miwork/api_user.py
miwork/dt_application.py
miwork/dt_approval.py
miwork/dt_calendar.py
miwork/dt_callback.py
miwork/dt_code.py
miwork/dt_contact.py
miwork/dt_drive.py
miwork/dt_enum.py
miwork/dt_help.py
miwork/dt_meeting_room.py
miwork/dt_message.py
miwork/dt_pay.py
miwork/dt_req.py
miwork/exception.py
miwork/feishu.py
miwork/helper.py
miwork/img.png
miwork/internal_cache.py
MiWork-2021.2.20.20.8.11.dist-info/LICENSE
MiWork-2021.2.20.20.8.11.dist-info/METADATA
MiWork-2021.2.20.20.8.11.dist-info/WHEEL
MiWork-2021.2.20.20.8.11.dist-info/entry_points.txt
MiWork-2021.2.20.20.8.11.dist-info/top_level.txt
MiWork-2021.2.20.20.8.11.dist-info/RECORD
