Metadata-Version: 2.1
Name: MiWork
Version: 2021.2.20.20.8.11
Summary: description
Home-page: https://github.com/Jie-Yuan/MiWork
Author: YuanJie
Author-email: 313303303@qq.com
Maintainer: JieYuan
Maintainer-email: 313303303@qq.com
License: Apache
Keywords: tool wheel,yuanjie,utils
Platform: all
Classifier: Operating System :: OS Independent
Classifier: Intended Audience :: Developers
Classifier: License :: OSI Approved :: MIT License
Classifier: Programming Language :: Python
Classifier: Programming Language :: Python :: Implementation
Requires-Dist: requests (<3.0.0,>=2.2)
Requires-Dist: pycryptodome (<4.0.0,>=3.9.0)
Requires-Dist: attrs (<20.0.0,>=19.0.0)
Requires-Dist: python-dateutil (<3.0.0,>=2.8.0)
Requires-Dist: dataframe-image
